enforce_git_message
