Metadata-Version: 2.1
Name: enforce-git-message
Version: 1.0.1
Summary: Enforces conventional git commit messages for git repositories
Home-page: https://github.com/prahladyeri/enforce-git-message
Author: Prahlad Yeri
Author-email: prahladyeri@yahoo.com
License: MIT
Keywords: security,scanner
Platform: UNKNOWN
Classifier: Programming Language :: Python :: 3
Classifier: License :: OSI Approved :: MIT License
Classifier: Operating System :: OS Independent
Requires-Python: >= 3.4
